lensecam/__init__.py
lensecam/camera_thread.py
lensecam/basler/__init__.py
lensecam/basler/camera_basler.py
lensecam/basler/camera_basler_others.txt
lensecam/basler/camera_basler_widget.py
lensecam/basler/camera_list.py
lensecam/basler/default_params.txt
lensecam/basler/mini_params.txt
lensecam/ids/__init__.py
lensecam/ids/camera_ids.py
lensecam/ids/camera_ids_widget.py
lensecam/ids/camera_list.py
lensecam-0.3.8.dist-info/METADATA
lensecam-0.3.8.dist-info/WHEEL
lensecam-0.3.8.dist-info/RECORD
