Metadata-Version: 2.4
Name: lensecam
Version: 0.3.8
Summary: LEnsE Camera Package / IDS and Basler API
Project-URL: Homepage, https://github.com/IOGS-LEnsE-ressources/lensecam
Author-email: Julien VILLEMEJANE <julien.villemejane@institutoptique.fr>
Classifier: License :: OSI Approved :: MIT License
Classifier: Operating System :: OS Independent
Classifier: Programming Language :: Python :: 3
Requires-Python: >=3.8
